RitikSrivastav/__init__.py
RitikSrivastav/perceptron.py
RitikSrivastav_pkg_Ritik_Srivastav-0.0.2.dist-info/LICENSE
RitikSrivastav_pkg_Ritik_Srivastav-0.0.2.dist-info/METADATA
RitikSrivastav_pkg_Ritik_Srivastav-0.0.2.dist-info/WHEEL
RitikSrivastav_pkg_Ritik_Srivastav-0.0.2.dist-info/top_level.txt
RitikSrivastav_pkg_Ritik_Srivastav-0.0.2.dist-info/RECORD
