Metadata-Version: 2.1
Name: RitikSrivastav-pkg-Ritik-Srivastav
Version: 0.0.2
Summary: a small package for perceptron
Home-page: https://github.com/Ritik-Srivastav/RitikSrivastav-pkg
Author: Ritik-Srivastav
Author-email: ritiksrivastav773@gmail.com
Project-URL: Bug Tracker, https://github.com/Ritik-Srivastav/RitikSrivastav-pkg/issues
Classifier: Programming Language :: Python :: 3
Classifier: License :: OSI Approved :: MIT License
Classifier: Operating System :: OS Independent
Requires-Python: >=3.6
License-File: LICENSE
Requires-Dist: numpy ==1.21.6
Requires-Dist: pandas ==1.1.5
Requires-Dist: joblib ==1.1.0
